auto_i18n_lib-0.1.3.dist-info/licenses/LICENSE
autoi18n/__init__.py
autoi18n/cache.py
autoi18n/cli.py
autoi18n/glossary.py
autoi18n/translator.py
autoi18n/utils.py
auto_i18n_lib-0.1.3.dist-info/METADATA
auto_i18n_lib-0.1.3.dist-info/WHEEL
auto_i18n_lib-0.1.3.dist-info/top_level.txt
auto_i18n_lib-0.1.3.dist-info/RECORD
