Metadata-Version: 2.4
Name: auto-i18n-lib
Version: 0.1.3
Summary: Dynamic HTML translation with OpenAI
Author-email: Your Name <you@example.com>
License: MIT
Requires-Python: >=3.9
License-File: LICENSE
Dynamic: license-file
